rcc_server/__init__.py
rcc_server/rcc_server.py
thinkingdata_test-0.3.dist-info/METADATA
thinkingdata_test-0.3.dist-info/WHEEL
thinkingdata_test-0.3.dist-info/top_level.txt
thinkingdata_test-0.3.dist-info/RECORD
