Metadata-Version: 2.1
Name: thinkingdata_test
Version: 0.3
Summary: come from thinkingdata QA team
Home-page: https://github.com/wengrongpo/thinkingdata_test
Author: wengrongpo
Author-email: rapi.weng@thinkingdata.cn
Classifier: Programming Language :: Python :: 3
Classifier: License :: OSI Approved :: MIT License
